script_generate_mcp_ex0804/__init__.py
script_generate_mcp_ex0804-0.1.0.dist-info/WHEEL
script_generate_mcp_ex0804-0.1.0.dist-info/entry_points.txt
script_generate_mcp_ex0804-0.1.0.dist-info/METADATA
script_generate_mcp_ex0804-0.1.0.dist-info/RECORD
