Metadata-Version: 2.3
Name: script-generate-mcp-ex0804
Version: 0.1.0
Summary: Add your description here
Author: zqovo
Author-email: zqovo <1285626696@qq.com>
Requires-Dist: mcp[cli]>=1.12.3
Requires-Python: >=3.12
